{
  "timestamp": "2025-11-23T07:37:04.525044",
  "source_timestamp": "2025-11-23T07:35:10.956338",
  "user_query": "I love drawing",
  "careers": {
    "Top Majors Related to Drawing": {
      "Top Majors Specialist": {
        "description": "",
        "resources": [
          "https://tophat.com/students/",
          "https://tophat.com/",
          "https://app.tophat.com/login",
          "https://www.bls.gov/ooh/",
          "https://www.zippia.com/data-specialist-jobs/trends/",
          "https://research.com/degrees/best-college-majors-to-pursue",
          "https://m.youtube.com/watch?v=dhyh0HSt2G8",
          "https://m.youtube.com/watch?v=gvkB_N3v9bk",
          "https://www.youtube.com/@MajorMajorsShow"
        ],
        "salary": {
          "min": 0,
          "max": 0,
          "currency": "USD"
        },
        "job_examples": [],
        "db_match_count": 0
      },
      "Top Majors Analyst": {
        "description": "",
        "resources": [
          "https://tophat.com/students/",
          "https://tophat.com/",
          "https://app.tophat.com/login",
          "https://365datascience.com/career-advice/data-analyst-job-outlook-2025/",
          "https://www.bls.gov/ooh/math/data-scientists.htm",
          "https://research.com/advice/different-types-of-data-analytics-degrees-and-their-salaries",
          "https://m.youtube.com/watch?v=Dp9vCJKQzkY",
          "https://blog.skyvia.com/best-youtube-channels-data-analytics/",
          "https://www.placementpreparation.io/blog/best-youtube-channels-to-learn-data-analytics/"
        ],
        "salary": {
          "min": 90000.0,
          "max": 150000.0,
          "currency": "USD"
        },
        "job_examples": [
          {
            "job_title": "Data Analyst",
            "company": "Airbnb",
            "description": "Analyze user behavior and business metrics. Create data visualizations.",
            "salary_range": "$90k - $140k"
          },
          {
            "job_title": "Cybersecurity Analyst",
            "company": "Microsoft",
            "description": "Monitor and respond to security incidents. Implement security controls.",
            "salary_range": "$100k - $150k"
          }
        ],
        "db_match_count": 2
      },
      "Top Majors Consultant": {
        "description": "",
        "resources": [
          "https://tophat.com/students/",
          "https://tophat.com/",
          "https://app.tophat.com/login",
          "https://research.com/careers/finance-careers",
          "https://research.com/careers/highest-paying-finance-degree-jobs-and-careers",
          "https://research.com/careers/data-science-careers",
          "https://www.analyticsinsight.net/career/10-youtube-channels-for-management-consulting-2025-edition",
          "https://m.youtube.com/watch?v=91bGm-NBMdE",
          "https://www.tubics.com/rankings/industries/management-consulting"
        ],
        "salary": {
          "min": 90000.0,
          "max": 145000.0,
          "currency": "USD"
        },
        "job_examples": [
          {
            "job_title": "Software Consultant",
            "company": "Accenture",
            "description": "Advise clients on technology solutions. Implement custom software.",
            "salary_range": "$90k - $140k"
          },
          {
            "job_title": "Technical Consultant",
            "company": "Deloitte",
            "description": "Provide technical expertise to enterprise clients.",
            "salary_range": "$95k - $145k"
          }
        ],
        "db_match_count": 2
      }
    },
    "10 Best Degrees for Artists": {
      "10 Best Specialist": {
        "description": "",
        "resources": [
          "https://jobstars.com/professional-associations-organizations/",
          "https://www.careeronestop.org/Toolkit/Training/find-professional-associations.aspx",
          "https://www.healthcarerecruiter.org/professional-associations-organizations/",
          "https://www.zippia.com/data-specialist-jobs/trends/",
          "https://www.datacamp.com/blog/top-ten-analytics-careers",
          "https://careeraptitudes.com/career-insights/employment-projection",
          "https://en.wikipedia.org/wiki/10",
          "https://googology.fandom.com/wiki/List_of_powers_of_10",
          "https://sciencenotes.org/powers-ten-metric-prefixes/"
        ],
        "salary": {
          "min": 0,
          "max": 0,
          "currency": "USD"
        },
        "job_examples": [],
        "db_match_count": 0
      },
      "10 Best Analyst": {
        "description": "",
        "resources": [
          "https://www.analyticsdegrees.org/resources/analytics-associations-and-organizations/",
          "https://www.apbma.org/",
          "https://libguides.cfcc.edu/c.php?g=604688&p=4191138",
          "https://www.healthgrad.com/healthcare/data-analyst/",
          "https://365datascience.com/career-advice/data-analyst-job-outlook-2025/",
          "https://365datascience.com/career-advice/the-data-analyst-job-market/",
          "https://www.youtube.com/playlist?list=PLpyc33gOcbVB-nB4b1J2fR-8ieHVsmXVN",
          "https://www.youtube.com/watch?v=1-RifR8rEzY",
          "https://www.ranker.com/list/best-career-advice-youtube-channels/lila-reid"
        ],
        "salary": {
          "min": 90000.0,
          "max": 150000.0,
          "currency": "USD"
        },
        "job_examples": [
          {
            "job_title": "Data Analyst",
            "company": "Airbnb",
            "description": "Analyze user behavior and business metrics. Create data visualizations.",
            "salary_range": "$90k - $140k"
          },
          {
            "job_title": "Cybersecurity Analyst",
            "company": "Microsoft",
            "description": "Monitor and respond to security incidents. Implement security controls.",
            "salary_range": "$100k - $150k"
          }
        ],
        "db_match_count": 2
      },
      "10 Best Consultant": {
        "description": "",
        "resources": [
          "https://entrepreneurshq.com/consultant-certification/",
          "https://consulthon.com/challenge/500/which-are-the-top-5-best-recognized-business-consultancy-certificates/",
          "https://consulthon.com/challenge/500/1062/which-are-the-top-5-best-recognized-business-consultancy-certificates/",
          "https://www.zippia.com/data-consultant-jobs/",
          "https://www.casebasix.com/pages/top-consulting-firms-washington-dc",
          "https://www.verywellmind.com/the-9-highest-paying-psychology-careers-2794940",
          "https://www.youtube.com/playlist?list=PLvUDn7TI43nFsD6W91S7dLuMCsP0kYhO1",
          "https://www.tiktok.com/discover/best-consultancy-for-usa-interview-preparation-in-kathmandu",
          "https://www.fiverr.com/gigs/youtube-consultant"
        ],
        "salary": {
          "min": 90000.0,
          "max": 145000.0,
          "currency": "USD"
        },
        "job_examples": [
          {
            "job_title": "Software Consultant",
            "company": "Accenture",
            "description": "Advise clients on technology solutions. Implement custom software.",
            "salary_range": "$90k - $140k"
          },
          {
            "job_title": "Technical Consultant",
            "company": "Deloitte",
            "description": "Provide technical expertise to enterprise clients.",
            "salary_range": "$95k - $145k"
          }
        ],
        "db_match_count": 2
      }
    },
    "Drawing Major": {
      "Drawing Major Specialist": {
        "description": "",
        "resources": [
          "https://www.adda.org/",
          "https://new.masterdrawings.org/about/",
          "https://jobstars.com/professional-associations-organizations/",
          "https://research.com/careers/data-science-careers",
          "https://research.com/careers/highest-paying-psychology-careers",
          "https://www.careervillage.org/questions/942886/what-do-i-do-confused",
          "https://www.youtube.com/watch?v=C3f1J0Bq9e0",
          "https://climbtheladder.com/drawing-interview-questions/",
          "https://coreskills.interviewgemini.com/interviews/interview-questions-for-drawing/"
        ],
        "salary": {
          "min": 0,
          "max": 0,
          "currency": "USD"
        },
        "job_examples": [],
        "db_match_count": 0
      },
      "Drawing Major Analyst": {
        "description": "",
        "resources": [
          "https://www.investopedia.com/articles/professionals/120815/equity-research-career-path-and-qualifications.asp",
          "https://enhancv.com/resume-examples/corporate-financial-analyst/",
          "https://irizpro.in/top-5-interview-questions-from-an-analyst-professional/",
          "https://365datascience.com/career-advice/data-analyst-job-outlook-2025/",
          "https://www.bls.gov/ooh/math/data-scientists.htm",
          "https://www.dataryx.com/blog/being-data-analyst-2025",
          "https://www.youtube.com/watch?v=9VQAwhp27eU",
          "https://www.tiktok.com/discover/macroeconomic-analyst-interview",
          "https://decopy.ai/youtube-video-summarizer/"
        ],
        "salary": {
          "min": 90000.0,
          "max": 150000.0,
          "currency": "USD"
        },
        "job_examples": [
          {
            "job_title": "Data Analyst",
            "company": "Airbnb",
            "description": "Analyze user behavior and business metrics. Create data visualizations.",
            "salary_range": "$90k - $140k"
          },
          {
            "job_title": "Cybersecurity Analyst",
            "company": "Microsoft",
            "description": "Monitor and respond to security incidents. Implement security controls.",
            "salary_range": "$100k - $150k"
          }
        ],
        "db_match_count": 2
      },
      "Drawing Major Consultant": {
        "description": "",
        "resources": [
          "https://www.cadcrowd.com/hire/detail-drawing",
          "https://getgis.org/news/canada-issues-major-draw-for-healthcare-pr-lowering-crs-to-combat-staff-shortages",
          "http://www.kingassociatescpa.com/monthly-news",
          "https://www.bls.gov/ooh/architecture-and-engineering/drafters.htm",
          "https://www.zippia.com/consultant-jobs/trends/",
          "https://www.roberthalf.com/us/en/insights/salary-guide",
          "https://m.youtube.com/watch?v=C3f1J0Bq9e0",
          "https://m.youtube.com/watch?v=b4NlkA1NEV4",
          "https://www.indeed.com/career-advice/interviewing/artist-interview-questions"
        ],
        "salary": {
          "min": 90000.0,
          "max": 145000.0,
          "currency": "USD"
        },
        "job_examples": [
          {
            "job_title": "Software Consultant",
            "company": "Accenture",
            "description": "Advise clients on technology solutions. Implement custom software.",
            "salary_range": "$90k - $140k"
          },
          {
            "job_title": "Technical Consultant",
            "company": "Deloitte",
            "description": "Provide technical expertise to enterprise clients.",
            "salary_range": "$95k - $145k"
          }
        ],
        "db_match_count": 2
      }
    }
  }
}